HeliosMedPrep.py
__init__.py
HeliosMedPrep-0.0.2.dist-info/LICENSE
HeliosMedPrep-0.0.2.dist-info/METADATA
HeliosMedPrep-0.0.2.dist-info/WHEEL
HeliosMedPrep-0.0.2.dist-info/top_level.txt
HeliosMedPrep-0.0.2.dist-info/RECORD
