Metadata-Version: 2.1
Name: HeliosMedPrep
Version: 0.0.2
Summary: HeliosMedPrep
Author-email: Duc Le <ngocducdarkzonezero@example.com>
Requires-Python: >=3.7
License-File: LICENSE
Requires-Dist: requests >2.26.0
Requires-Dist: pandas
Requires-Dist: numpy
Requires-Dist: torch
Requires-Dist: tqdm
Requires-Dist: scikit-learn
